arxiv_get/__init__.py
arxiv_get/arxiv_get.py
arxiv_get/async_translator.py
arxiv_get/categories.py
arxiv_get/paper.py
arxiv_get-0.1.0.dist-info/METADATA
arxiv_get-0.1.0.dist-info/WHEEL
arxiv_get-0.1.0.dist-info/top_level.txt
arxiv_get-0.1.0.dist-info/RECORD
