Metadata-Version: 2.4
Name: arxiv_get
Version: 0.1.0
Summary: A awesome Python package
Home-page: https://github.com/HuPengsheet/EasyNN
Author: hupeng
Author-email: hupeng_2022@163.com
Classifier: Programming Language :: Python :: 3
Classifier: License :: OSI Approved :: MIT License
Classifier: Operating System :: OS Independent
